{
	"name": "pipeline1",
	"properties": {
		"activities": [
			{
				"name": "Copy data1",
				"type": "Copy",
				"dependsOn": [],
				"policy": {
					"timeout": "0.12:00:00",
					"retry": 0,
					"retryIntervalInSeconds": 30,
					"secureOutput": false,
					"secureInput": false
				},
				"userProperties": [],
				"typeProperties": {
					"source": {
						"type": "DelimitedTextSource",
						"storeSettings": {
							"type": "AzureBlobFSReadSettings",
							"recursive": true,
							"enablePartitionDiscovery": false
						},
						"formatSettings": {
							"type": "DelimitedTextReadSettings"
						}
					},
					"sink": {
						"type": "AzureSqlSink",
						"writeBehavior": "upsert",
						"upsertSettings": {
							"useTempDB": true,
							"keys": [
								"did"
							]
						},
						"sqlWriterUseTableLock": false,
						"disableMetricsCollection": false
					},
					"enableStaging": false,
					"translator": {
						"type": "TabularTranslator",
						"mappings": [
							{
								"source": {
									"name": "did",
									"type": "String",
									"physicalType": "String"
								},
								"sink": {
									"name": "did",
									"type": "Int32",
									"physicalType": "int"
								}
							},
							{
								"source": {
									"name": "dname",
									"type": "String",
									"physicalType": "String"
								},
								"sink": {
									"name": "dname",
									"type": "String",
									"physicalType": "varchar"
								}
							},
							{
								"source": {
									"name": "revenue",
									"type": "String",
									"physicalType": "String"
								},
								"sink": {
									"name": "revenue",
									"type": "Int32",
									"physicalType": "int"
								}
							}
						],
						"typeConversion": true,
						"typeConversionSettings": {
							"allowDataTruncation": true,
							"treatBooleanAsNumber": false
						}
					}
				},
				"inputs": [
					{
						"referenceName": "sourcedataset",
						"type": "DatasetReference"
					}
				],
				"outputs": [
					{
						"referenceName": "targetdataset1",
						"type": "DatasetReference"
					}
				]
			}
		],
		"annotations": [],
		"lastPublishTime": "2022-10-10T09:17:17Z"
	},
	"type": "Microsoft.DataFactory/factories/pipelines"
}